{
  "_fv": 43,
  "_type": "loottable",
  "definition": {
    "type": "Block",
    "pools": [
      {
        "minrolls": 0,
        "maxrolls": 2,
        "minbonusrolls": 1,
        "maxbonusrolls": 1,
        "hasbonusrolls": false,
        "entries": [
          {
            "type": "item",
            "item": {
              "value": "CUSTOM:Pirate.helmet"
            },
            "weight": 1,
            "minCount": 1,
            "maxCount": 1,
            "minEnchantmentLevel": 0,
            "maxEnchantmentLevel": 0,
            "affectedByFortune": false,
            "explosionDecay": false,
            "silkTouchMode": 0
          },
          {
            "type": "item",
            "item": {
              "value": "CUSTOM:Pirate.body"
            },
            "weight": 1,
            "minCount": 1,
            "maxCount": 1,
            "minEnchantmentLevel": 0,
            "maxEnchantmentLevel": 0,
            "affectedByFortune": false,
            "explosionDecay": false,
            "silkTouchMode": 0
          },
          {
            "type": "item",
            "item": {
              "value": "CUSTOM:HematiteInfusedAnchor"
            },
            "weight": 1,
            "minCount": 1,
            "maxCount": 1,
            "minEnchantmentLevel": 0,
            "maxEnchantmentLevel": 0,
            "affectedByFortune": false,
            "explosionDecay": false,
            "silkTouchMode": 0
          }
        ]
      },
      {
        "minrolls": 1,
        "maxrolls": 3,
        "minbonusrolls": 1,
        "maxbonusrolls": 1,
        "hasbonusrolls": false,
        "entries": [
          {
            "type": "item",
            "item": {
              "value": "Items.SUSPICIOUS_STEW"
            },
            "weight": 1,
            "minCount": 1,
            "maxCount": 1,
            "minEnchantmentLevel": 0,
            "maxEnchantmentLevel": 0,
            "affectedByFortune": false,
            "explosionDecay": false,
            "silkTouchMode": 0
          },
          {
            "type": "item",
            "item": {
              "value": "Items.COOKED_FISH#1"
            },
            "weight": 5,
            "minCount": 1,
            "maxCount": 6,
            "minEnchantmentLevel": 0,
            "maxEnchantmentLevel": 0,
            "affectedByFortune": false,
            "explosionDecay": false,
            "silkTouchMode": 0
          },
          {
            "type": "item",
            "item": {
              "value": "Items.COOKED_FISH#0"
            },
            "weight": 5,
            "minCount": 1,
            "maxCount": 6,
            "minEnchantmentLevel": 0,
            "maxEnchantmentLevel": 0,
            "affectedByFortune": false,
            "explosionDecay": false,
            "silkTouchMode": 0
          },
          {
            "type": "item",
            "item": {
              "value": "Items.BREAD"
            },
            "weight": 2,
            "minCount": 1,
            "maxCount": 3,
            "minEnchantmentLevel": 0,
            "maxEnchantmentLevel": 0,
            "affectedByFortune": false,
            "explosionDecay": false,
            "silkTouchMode": 0
          },
          {
            "type": "item",
            "item": {
              "value": "Items.DRIED_KELP"
            },
            "weight": 3,
            "minCount": 1,
            "maxCount": 6,
            "minEnchantmentLevel": 0,
            "maxEnchantmentLevel": 0,
            "affectedByFortune": false,
            "explosionDecay": false,
            "silkTouchMode": 0
          }
        ]
      },
      {
        "minrolls": 1,
        "maxrolls": 3,
        "minbonusrolls": 1,
        "maxbonusrolls": 1,
        "hasbonusrolls": false,
        "entries": [
          {
            "type": "item",
            "item": {
              "value": "CUSTOM:LeadIngot"
            },
            "weight": 10,
            "minCount": 1,
            "maxCount": 3,
            "minEnchantmentLevel": 0,
            "maxEnchantmentLevel": 0,
            "affectedByFortune": false,
            "explosionDecay": false,
            "silkTouchMode": 0
          },
          {
            "type": "item",
            "item": {
              "value": "CUSTOM:RawLead"
            },
            "weight": 15,
            "minCount": 1,
            "maxCount": 3,
            "minEnchantmentLevel": 0,
            "maxEnchantmentLevel": 0,
            "affectedByFortune": false,
            "explosionDecay": false,
            "silkTouchMode": 0
          },
          {
            "type": "item",
            "item": {
              "value": "CUSTOM:ZincSheet"
            },
            "weight": 20,
            "minCount": 1,
            "maxCount": 15,
            "minEnchantmentLevel": 0,
            "maxEnchantmentLevel": 0,
            "affectedByFortune": false,
            "explosionDecay": false,
            "silkTouchMode": 0
          },
          {
            "type": "item",
            "item": {
              "value": "Items.IRON_INGOT"
            },
            "weight": 20,
            "minCount": 1,
            "maxCount": 10,
            "minEnchantmentLevel": 0,
            "maxEnchantmentLevel": 0,
            "affectedByFortune": false,
            "explosionDecay": false,
            "silkTouchMode": 0
          },
          {
            "type": "item",
            "item": {
              "value": "Items.IRON_NUGGET"
            },
            "weight": 20,
            "minCount": 1,
            "maxCount": 20,
            "minEnchantmentLevel": 0,
            "maxEnchantmentLevel": 0,
            "affectedByFortune": false,
            "explosionDecay": false,
            "silkTouchMode": 0
          },
          {
            "type": "item",
            "item": {
              "value": "Items.COPPER_INGOT"
            },
            "weight": 20,
            "minCount": 1,
            "maxCount": 7,
            "minEnchantmentLevel": 0,
            "maxEnchantmentLevel": 0,
            "affectedByFortune": false,
            "explosionDecay": false,
            "silkTouchMode": 0
          }
        ]
      },
      {
        "minrolls": 0,
        "maxrolls": 1,
        "minbonusrolls": 1,
        "maxbonusrolls": 1,
        "hasbonusrolls": false,
        "entries": [
          {
            "type": "item",
            "item": {
              "value": "CUSTOM:Bullet"
            },
            "weight": 1,
            "minCount": 0,
            "maxCount": 64,
            "minEnchantmentLevel": 0,
            "maxEnchantmentLevel": 0,
            "affectedByFortune": false,
            "explosionDecay": false,
            "silkTouchMode": 0
          }
        ]
      }
    ],
    "name": "blocks/pirate_barrel",
    "namespace": "mod"
  }
}